hippynn/__init__.py
hippynn/_settings_setup.py
hippynn/_version.py
hippynn/pretraining.py
hippynn/tools.py
hippynn/custom_kernels/__init__.py
hippynn/custom_kernels/autograd_wrapper.py
hippynn/custom_kernels/env_atomic.py
hippynn/custom_kernels/env_cupy.py
hippynn/custom_kernels/env_numba.py
hippynn/custom_kernels/env_pytorch.py
hippynn/custom_kernels/env_sparse.py
hippynn/custom_kernels/env_triton.py
hippynn/custom_kernels/fast_convert.py
hippynn/custom_kernels/registry.py
hippynn/custom_kernels/tensor_wrapper.py
hippynn/custom_kernels/test_env.py
hippynn/custom_kernels/test_speed_env.py
hippynn/custom_kernels/utils.py
hippynn/databases/SNAPJson.py
hippynn/databases/__init__.py
hippynn/databases/_ani_reader.py
hippynn/databases/database.py
hippynn/databases/h5_pyanitools.py
hippynn/databases/ondisk.py
hippynn/databases/restarter.py
hippynn/experiment/__init__.py
hippynn/experiment/assembly.py
hippynn/experiment/controllers.py
hippynn/experiment/device.py
hippynn/experiment/evaluator.py
hippynn/experiment/lightning_trainer.py
hippynn/experiment/metric_tracker.py
hippynn/experiment/routines.py
hippynn/experiment/serialization.py
hippynn/experiment/step_functions.py
hippynn/graphs/__init__.py
hippynn/graphs/ensemble.py
hippynn/graphs/gops.py
hippynn/graphs/graph.py
hippynn/graphs/predictor.py
hippynn/graphs/viz.py
hippynn/graphs/indextransformers/__init__.py
hippynn/graphs/indextransformers/atoms.py
hippynn/graphs/indextransformers/pairs.py
hippynn/graphs/indextransformers/tensors.py
hippynn/graphs/indextypes/__init__.py
hippynn/graphs/indextypes/reduce_funcs.py
hippynn/graphs/indextypes/registry.py
hippynn/graphs/indextypes/type_def.py
hippynn/graphs/nodes/__init__.py
hippynn/graphs/nodes/_option.py
hippynn/graphs/nodes/excited.py
hippynn/graphs/nodes/indexers.py
hippynn/graphs/nodes/inputs.py
hippynn/graphs/nodes/loss.py
hippynn/graphs/nodes/misc.py
hippynn/graphs/nodes/networks.py
hippynn/graphs/nodes/pairs.py
hippynn/graphs/nodes/physics.py
hippynn-0.1.3.dist-info/licenses/AUTHORS.txt
hippynn-0.1.3.dist-info/licenses/LICENSE.txt
hippynn-0.1.3.dist-info/METADATA
hippynn-0.1.3.dist-info/WHEEL
hippynn-0.1.3.dist-info/top_level.txt
hippynn-0.1.3.dist-info/RECORD
