Metadata-Version: 2.4
Name: hippynn
Version: 0.1.3
Summary: The hippynn python package - a modular library for atomistic machine learning with pytorch
Author-email: Nicholas Lubbers et al <hippynn@lanl.gov>
License: BSD 3-Clause License
Classifier: Development Status :: 3 - Alpha
Classifier: Intended Audience :: Science/Research
Classifier: Programming Language :: Python :: 3
Classifier: Topic :: Scientific/Engineering :: Physics
Classifier: Topic :: Scientific/Engineering :: Chemistry
Classifier: Topic :: Software Development :: Libraries
Requires-Python: >=3.9
License-File: LICENSE.txt
License-File: AUTHORS.txt
Requires-Dist: numpy
Requires-Dist: torch>2.0
Provides-Extra: docs
Requires-Dist: sphinx>=8.0; extra == "docs"
Requires-Dist: sphinx_rtd_theme>=3.0.0rc1; extra == "docs"
Requires-Dist: sphinxcontrib-bibtex>=2.6; extra == "docs"
Provides-Extra: full
Requires-Dist: ase; extra == "full"
Requires-Dist: numba; extra == "full"
Requires-Dist: matplotlib; extra == "full"
Requires-Dist: tqdm; extra == "full"
Requires-Dist: graphviz; extra == "full"
Requires-Dist: h5py; extra == "full"
Requires-Dist: lightning; extra == "full"
Requires-Dist: scipy; extra == "full"
Requires-Dist: opt_einsum; extra == "full"
Dynamic: license-file
